estev
