Metadata-Version: 1.0
Name: estev.ao-cli
Version: 0.2.1
Summary: A CLI to create shortener urls
Home-page: https://github.com/nelsonmestevao/estev.ao-cli
Author: Nelson Estevão
Author-email: hello@estevao.xyz
License: UNKNOWN
Platform: UNKNOWN
